{
 "Week": "2025-07-23",
 "LastWeek": "",
 "X": 0.4018599491507626,
 "Programs": [
  {
   "Program": "cmd/asm",
   "Version": "go1.24.5",
   "GoVersion": "go1.24.5",
   "GOOS": "linux",
   "GOARCH": "amd64",
   "Counters": {
    "asm/flag:D": 40,
    "asm/flag:I": 40,
    "asm/flag:gensymabis": 18,
    "asm/flag:o": 40,
    "asm/flag:p": 40,
    "asm/flag:shared": 40,
    "asm/flag:trimpath": 40,
    "asm/invocations": 40
   },
   "Stacks": {}
  },
  {
   "Program": "cmd/cgo",
   "Version": "go1.24.5",
   "GoVersion": "go1.24.5",
   "GOOS": "linux",
   "GOARCH": "amd64",
   "Counters": {
    "cgo/flag:dynimport": 7,
    "cgo/flag:dynlinker": 1,
    "cgo/flag:dynout": 7,
    "cgo/flag:dynpackage": 7,
    "cgo/flag:import_runtime_cgo": 1,
    "cgo/flag:import_syscall": 1,
    "cgo/flag:importpath": 7,
    "cgo/flag:ldflags": 7,
    "cgo/flag:objdir": 7,
    "cgo/invocations": 14
   },
   "Stacks": {}
  },
  {
   "Program": "cmd/compile",
   "Version": "go1.24.5",
   "GoVersion": "go1.24.5",
   "GOOS": "linux",
   "GOARCH": "amd64",
   "Counters": {
    "compile/flag:asmhdr": 18,
    "compile/flag:buildid": 1975,
    "compile/flag:c": 1975,
    "compile/flag:complete": 1949,
    "compile/flag:dwarf": 1,
    "compile/flag:embedcfg": 4,
    "compile/flag:goversion": 1975,
    "compile/flag:importcfg": 1975,
    "compile/flag:installsuffix": 1975,
    "compile/flag:lang": 1975,
    "compile/flag:nolocalimports": 1975,
    "compile/flag:o": 1975,
    "compile/flag:p": 1975,
    "compile/flag:pack": 1975,
    "compile/flag:shared": 1975,
    "compile/flag:std": 41,
    "compile/flag:symabis": 18,
    "compile/flag:trimpath": 1975,
    "compile/invocations": 1991
   },
   "Stacks": {}
  },
  {
   "Program": "cmd/go",
   "Version": "go1.24.5",
   "GoVersion": "go1.24.5",
   "GOOS": "linux",
   "GOARCH": "amd64",
   "Counters": {
    "go/build/flag/buildmode:pie": 3,
    "go/build/flag:buildmode": 3,
    "go/build/flag:gcflags": 2,
    "go/build/flag:ldflags": 3,
    "go/build/flag:mod": 3,
    "go/build/flag:modcacherw": 3,
    "go/build/flag:modfile": 2,
    "go/build/flag:o": 3,
    "go/build/flag:tags": 3,
    "go/build/flag:trimpath": 3,
    "go/buildcache/hit": 967,
    "go/buildcache/miss": 1979,
    "go/buildcache/stdlib-recompiled": 2,
    "go/goroot:usr-lib-go": 46,
    "go/invocations": 46,
    "go/mode:gopath": 43,
    "go/mode:module": 3,
    "go/platform/host/linux/major-version:6": 46,
    "go/platform/host/linux/version:6-15": 46,
    "go/platform/target/goamd64:v1": 46,
    "go/platform/target/goarch:amd64": 46,
    "go/platform/target/goos:linux": 46,
    "go/run/flag/buildmode:pie": 1,
    "go/run/flag:buildmode": 1,
    "go/run/flag:ldflags": 1,
    "go/run/flag:mod": 1,
    "go/run/flag:modcacherw": 1,
    "go/run/flag:modfile": 1,
    "go/run/flag:tags": 1,
    "go/run/flag:trimpath": 1,
    "go/subcommand:build": 3,
    "go/subcommand:env": 42,
    "go/subcommand:run": 1
   },
   "Stacks": {}
  },
  {
   "Program": "cmd/link",
   "Version": "go1.24.5",
   "GoVersion": "go1.24.5",
   "GOOS": "linux",
   "GOARCH": "amd64",
   "Counters": {
    "link/flag:B": 1,
    "link/flag:X": 4,
    "link/flag:buildid": 4,
    "link/flag:buildmode": 4,
    "link/flag:extld": 4,
    "link/flag:importcfg": 4,
    "link/flag:installsuffix": 4,
    "link/flag:o": 4,
    "link/flag:s": 1,
    "link/flag:w": 3,
    "link/invocations": 8
   },
   "Stacks": {}
  }
 ],
 "Config": "v0.0.0-0"
}